[
  { "id": 3182, "label": { "en": "Biker Mice from Mars", "es": "Motorratones de Marte" } },
  { "id": 7394, "label": { "en": "Bionic Six", "es": "Bionic Six" } },
  { "id": 2856, "label": { "en": "Bravestarr", "es": "Bravestarr" } },
  { "id": 9147, "label": { "en": "Captain Planet", "es": "Capitán Planeta" } },
  { "id": 4721, "label": { "en": "DC Comics", "es": "DC Comics" } },
  { "id": 6283, "label": { "en": "Dino-riders", "es": "Dino-riders" } },
  { "id": 1945, "label": { "en": "Dragon ball", "es": "Dragon ball" } },
  { "id": 5638, "label": { "en": "Dragon Quest", "es": "Dragon Quest" } },
  { "id": 8529, "label": { "en": "Extreme Dinosaurs", "es": "Extreme Dinosaurs" } },
  { "id": 2174, "label": { "en": "G.I. Joe", "es": "G.I. Joe" } },
  { "id": 4915, "label": { "en": "Gargoyles", "es": "Gárgolas" } },
  { "id": 7362, "label": { "en": "Ghostbusters", "es": "Cazafantasmas" } },
  { "id": 3587, "label": { "en": "Jurassic Park", "es": "Parque Jurásico" } },
  { "id": 6841, "label": { "en": "Marvel Comics", "es": "Marvel Comics" } },
  { "id": 1293, "label": { "en": "Masters of the Universe", "es": "Masters del Universo" } },
  { "id": 5426, "label": { "en": "Pokemon", "es": "Pokemon" } },
  { "id": 9658, "label": { "en": "Power Rangers", "es": "Power Rangers" } },
  { "id": 2739, "label": { "en": "Saint Seiya", "es": "Caballeros del Zodiaco" } },
  { "id": 8164, "label": { "en": "Silverhawks", "es": "Silverhawks" } },
  { "id": 4382, "label": { "en": "Space Jam", "es": "Space Jam" } },
  { "id": 7925, "label": { "en": "Star Wars", "es": "Star Wars" } },
  { "id": 1576, "label": { "en": "Street Sharks", "es": "Street Sharks" } },
  { "id": 6249, "label": { "en": "ThunderCats", "es": "ThunderCats" } },
  { "id": 3814, "label": { "en": "TMNT", "es": "Tortugas Ninja" } },
  { "id": 5197, "label": { "en": "Toxic Crusaders", "es": "Toxic Crusaders" } },
  { "id": 9436, "label": { "en": "Transformers", "es": "Transformers" } },
  { "id": 2681, "label": { "en": "Wrestling", "es": "Lucha Libre" } }
]